[
	{
		"actor_name": "Sean Connery",
		"id": "connery",
		"titles": [
			"Dr. No",
			"From Russia With Love",
			"Goldfinger",
			"Thunderball",
			"You Only Live Twice",
			"Diamonds Are Forever",
			"Never Say Never Again"
		]
	},
	{
		"actor_name": "George Lazenby",
		"id": "lazenby",
		"titles": [
			"On Her Majesty's Secret Service"
		]
	},
	{
		"actor_name": "Roger Moore",
		"id": "moore",
		"titles": [
			"Live And Let Die",
			"The Man With The Golden Gun",
			"The Spy Who Loved Me",
			"Moonraker",
			"For Your Eyes Only",
			"Octopussy",
			"A View To A Kill"
		]
	},
	{
		"actor_name": "Timothy Dalton",
		"id": "dalton",
		"titles": [
			"The Living Daylights",
			"Licence To Kill"
		]
	},
	{
		"actor_name": "Pierce Brosnan",
		"id": "brosnan",
		"titles": [
			"Goldeneye",
			"Tomorrow Never Dies",
			"The World Is Not Enough",
			"Die Another Day"
		]
	},
	{
		"actor_name": "Daniel Craig",
		"id": "craig",
		"titles": [
			"Casino Royale",
			"Quantum Of Solace",
			"Skyfall",
			"Spectre"
		]
	}
]
